dynamic_baml/__init__.py
dynamic_baml/baml_executor.py
dynamic_baml/core.py
dynamic_baml/exceptions.py
dynamic_baml/providers.py
dynamic_baml/py.typed
dynamic_baml/schema_generator.py
dynamic_baml/types.py
dynamic_baml/baml/__init__.py
dynamic_baml/baml/async_client.py
dynamic_baml/baml/async_request.py
dynamic_baml/baml/clients.baml
dynamic_baml/baml/config.py
dynamic_baml/baml/generators.baml
dynamic_baml/baml/globals.py
dynamic_baml/baml/inlinedbaml.py
dynamic_baml/baml/parser.py
dynamic_baml/baml/partial_types.py
dynamic_baml/baml/resume.baml
dynamic_baml/baml/sync_client.py
dynamic_baml/baml/sync_request.py
dynamic_baml/baml/tracing.py
dynamic_baml/baml/type_builder.py
dynamic_baml/baml/types.py
dynamic_baml-0.2.0.dist-info/licenses/LICENSE
dynamic_baml-0.2.0.dist-info/METADATA
dynamic_baml-0.2.0.dist-info/WHEEL
dynamic_baml-0.2.0.dist-info/top_level.txt
dynamic_baml-0.2.0.dist-info/RECORD
