Metadata-Version: 2.4
Name: dynamic-baml
Version: 0.2.0
Summary: A standalone library for dynamic BoundaryML schema generation and LLM response parsing
Home-page: https://github.com/roboalchemist/dynamic-baml
Author: Dynamic BAML Team
Author-email: PM Bot Project <dev@pmbot.dev>
License: MIT
Project-URL: Homepage, https://github.com/pm-bot/dynamic-baml
Project-URL: Documentation, https://dynamic-baml.readthedocs.io/
Project-URL: Repository, https://github.com/pm-bot/dynamic-baml.git
Project-URL: Issues, https://github.com/pm-bot/dynamic-baml/issues
Keywords: llm,baml,schema,parsing,ai,structured-data
Classifier: Development Status :: 3 - Alpha
Classifier: Intended Audience :: Developers
Classifier: License :: OSI Approved :: MIT License
Classifier: Programming Language :: Python :: 3
Classifier: Programming Language :: Python :: 3.8
Classifier: Programming Language :: Python :: 3.9
Classifier: Programming Language :: Python :: 3.10
Classifier: Programming Language :: Python :: 3.11
Classifier: Programming Language :: Python :: 3.12
Classifier: Topic :: Software Development :: Libraries :: Python Modules
Classifier: Topic :: Scientific/Engineering :: Artificial Intelligence
Requires-Python: >=3.8
License-File: LICENSE
Requires-Dist: baml-py>=0.89.0
Requires-Dist: httpx>=0.24.0
Requires-Dist: pydantic>=2.0.0
Requires-Dist: pyyaml>=6.0.0
Provides-Extra: dev
Requires-Dist: pytest>=7.0.0; extra == "dev"
Requires-Dist: pytest-asyncio>=0.21.0; extra == "dev"
Requires-Dist: pytest-cov>=4.0.0; extra == "dev"
Requires-Dist: black>=23.0.0; extra == "dev"
Requires-Dist: isort>=5.12.0; extra == "dev"
Requires-Dist: mypy>=1.0.0; extra == "dev"
Requires-Dist: ruff>=0.0.290; extra == "dev"
Provides-Extra: test
Requires-Dist: pytest>=7.0.0; extra == "test"
Requires-Dist: pytest-asyncio>=0.21.0; extra == "test"
Requires-Dist: pytest-cov>=4.0.0; extra == "test"
Dynamic: author
Dynamic: home-page
Dynamic: license-file
Dynamic: requires-python
